[{"sort": true, "filter": {"options": [], "placeholder": "\u8f38\u5165", "closeDropdownOnSelection": false, "mode": "multi", "type": "select", "init": {"value": []}}, "label": "\u4ee3\u865f", "name": "b_info.code"}, {"sort": true, "label": "\u540d\u7a31", "name": "b_info.name"}, {"sort": true, "label": "\u80a1\u50f9\u65e5\u671f", "name": "d_cont.date"}, {"sort": true, "label": "\u6210\u4ea4", "name": "b_info.price"}, {"sort": true, "label": "\u6f32\u8dcc\u50f9", "name": "b_info.change"}, {"sort": true, "label": "\u6f32\u8dcc\u5e45", "name": "b_info.pct"}, {"sort": true, "label": "\u6210\u4ea4\u5f35\u6578", "name": "d_cont.volume"}, {"sort": true, "label": "\u80a1\u5229\u767c\u653e\u5e74\u5ea6", "name": "d_cont.year"}, {"sort": true, "label": "\u73fe\u91d1\u80a1\u5229\u9023\u914d\u6b21\u6578", "name": "d_cont.cont1"}, {"sort": true, "label": "\u73fe\u91d1\u80a1\u5229\u9023\u914d\u7e3d\u984d(\u5143)", "name": "d_cont.cont2"}, {"sort": true, "label": "\u73fe\u91d1\u80a1\u5229\u9023\u914d\u5747\u984d(\u5143)", "name": "d_cont.cont3"}, {"sort": true, "label": "\u914d\u606f\u5747\u984d\u9664\u4ee5\u80a1\u50f9(%)", "name": "d_cont.cont4"}, {"sort": true, "label": "\u80a1\u7968\u80a1\u5229\u9023\u914d\u6b21\u6578", "name": "d_cont.cont5"}, {"sort": true, "label": "\u80a1\u7968\u80a1\u5229\u9023\u914d\u7e3d\u984d(\u5143)", "name": "d_cont.cont6"}, {"sort": true, "label": "\u80a1\u7968\u80a1\u5229\u9023\u914d\u5747\u984d(\u5143)", "name": "d_cont.cont7"}, {"sort": true, "label": "\u914d\u80a1\u5747\u984d\u9664\u4ee5\u80a1\u50f9(%)", "name": "d_cont.cont8"}, {"sort": true, "label": "\u5408\u8a08\u80a1\u5229\u9023\u914d\u6b21\u6578", "name": "d_cont.cont9"}, {"sort": true, "label": "\u5408\u8a08\u80a1\u5229\u9023\u914d\u7e3d\u984d(\u5143)", "name": "d_cont.cont10"}, {"sort": true, "label": "\u5408\u8a08\u80a1\u5229\u9023\u914d\u5747\u984d(\u5143)", "name": "d_cont.cont11"}, {"sort": true, "label": "\u80a1\u5229\u5747\u984d\u9664\u4ee5\u80a1\u50f9(%)", "name": "d_cont.cont12"}]