[{"sort": true, "filter": {"closeDropdownOnSelection": false, "placeholder": "\u8f38\u5165", "mode": "multi", "type": "select", "options": [], "init": {"value": []}}, "name": "b_info.code", "label": "\u4ee3\u865f"}, {"sort": true, "name": "b_info.name", "label": "\u540d\u7a31"}, {"sort": true, "name": "b_info.price", "label": "\u6210\u4ea4"}, {"sort": true, "name": "b_info.change", "label": "\u6f32\u8dcc\u50f9"}, {"sort": true, "name": "b_info.pct", "label": "\u6f32\u8dcc\u5e45"}, {"sort": true, "name": "y_eps.yeps", "label": "\u5e73\u5747EPS(\u5143)"}, {"sort": true, "name": "y_eps.yeps1", "label": "2008EPS(\u5143)"}, {"sort": true, "name": "y_eps.yeps2", "label": "2009EPS(\u5143)"}, {"sort": true, "name": "y_eps.yeps3", "label": "2010EPS(\u5143)"}, {"sort": true, "name": "y_eps.yeps4", "label": "2011EPS(\u5143)"}, {"sort": true, "name": "y_eps.yeps5", "label": "2012EPS(\u5143)"}, {"sort": true, "name": "y_eps.yeps6", "label": "2013EPS(\u5143)"}, {"sort": true, "name": "y_eps.yeps7", "label": "2014EPS(\u5143)"}, {"sort": true, "name": "y_eps.yeps8", "label": "2015EPS(\u5143)"}, {"sort": true, "name": "y_eps.yeps9", "label": "2016EPS(\u5143)"}, {"sort": true, "name": "y_eps.yeps10", "label": "2017EPS(\u5143)"}, {"sort": true, "name": "y_eps.yeps11", "label": "2018EPS(\u5143)"}, {"sort": true, "name": "y_eps.yeps12", "label": "2019EPS(\u5143)"}]