[
    {
      "label": "代號",
      "name": "b_info.code",
      "filter": {
        "type": "select",
        "mode": "multi",
        "closeDropdownOnSelection": false,
        "placeholder": "輸入",
        "options": [],
        "init": {
          "value": []
        }
      },
      "sort": true
    },
    {
      "label": "名稱",
      "name": "b_info.name",
      "sort": true
    },
    {
      "label": "成交",
      "name": "b_info.price",
      "sort": true
    },
    {
      "label": "漲跌價",
      "name": "b_info.change",
      "sort": true
    },
    {
      "label": "漲跌幅",
      "name": "b_info.pct",
      "sort": true
    },
    {
      "label": "法人買賣日期",
      "name": "c_foreign.date",
      "sort": true
    },
    {
      "label": "當日外本比",
      "name": "c_foreign.today",
      "sort": true
    },
    {
      "label": "2日外本比",
      "name": "c_foreign.day2",
      "sort": true
    },
    {
      "label": "3日外本比",
      "name": "c_foreign.day3",
      "sort": true
    },
    {
      "label": "5日外本比",
      "name": "c_foreign.day5",
      "sort": true
    },
    {
      "label": "10日外本比",
      "name": "c_foreign.day10",
      "sort": true
    },
    {
      "label": "一個月外本比",
      "name": "c_foreign.day30",
      "sort": true
    },
    {
      "label": "三個月外本比",
      "name": "c_foreign.day90",
      "sort": true
    },
    {
      "label": "半年外本比",
      "name": "c_foreign.day180",
      "sort": true
    },
    {
      "label": "今年外本比",
      "name": "c_foreign.year",
      "sort": true
    },
    {
      "label": "一年外本比",
      "name": "c_foreign.year1",
      "sort": true
    },
    {
      "label": "三年外本比",
      "name": "c_foreign.year3",
      "sort": true
    },
    {
      "label": "十年外本比",
      "name": "c_foreign.year10",
      "sort": true
    }
  ]