[{"dk_dies": {"ma240": 0.0, "volume": 523.0, "price": 67.15, "code": "0057", "change": -0.15, "name": "\u5bcc\u90a6\u6469\u53f0", "ma2400": 0.0, "ma60": 0.0, "ma10": 67.88, "ma30": 0.0, "ma20": 67.89, "ma5": 66.71, "pct": -0.22, "ma1200": 0.0, "ma480": 0.0, "date": "09/29", "ma720": 0.0}}, {"dk_dies": {"ma240": 19.36, "volume": 108.0, "price": 18.7, "code": "00682U", "change": -0.12, "name": "\u5143\u5927\u7f8e\u5143\u6307\u6578", "ma2400": 0.0, "ma60": 19.24, "ma10": 0.0, "ma30": 18.77, "ma20": 0.0, "ma5": 18.82, "pct": -0.64, "ma1200": 0.0, "ma480": 19.28, "date": "09/29", "ma720": 0.0}}, {"dk_dies": {"ma240": 13.67, "volume": 0.0, "price": 11.78, "code": "00691R", "change": 0.0, "name": "\u5146\u8c50\u85cd\u7c4c30\u53cd1", "ma2400": 0.0, "ma60": 12.91, "ma10": 0.0, "ma30": 11.83, "ma20": 0.0, "ma5": 0.0, "pct": 0.0, "ma1200": 0.0, "ma480": 15.08, "date": "09/29", "ma720": 15.78}}, {"dk_dies": {"ma240": 0.0, "volume": 0.5, "price": 116.2, "code": "008201", "change": -3.4, "name": "BP\u4e0a\u8b4950", "ma2400": 0.0, "ma60": 0.0, "ma10": 118.9, "ma30": 0.0, "ma20": 119.1, "ma5": 118.0, "pct": -2.84, "ma1200": 0.0, "ma480": 0.0, "date": "09/29", "ma720": 0.0}}, {"dk_dies": {"ma240": 22.68, "volume": 127.0, "price": 22.7, "code": "1437", "change": -0.1, "name": "\u52e4\u76ca\u63a7", "ma2400": 0.0, "ma60": 0.0, "ma10": 22.99, "ma30": 0.0, "ma20": 22.96, "ma5": 22.79, "pct": -0.44, "ma1200": 0.0, "ma480": 0.0, "date": "09/29", "ma720": 0.0}}, {"dk_dies": {"ma240": 10.4, "volume": 3413.0, "price": 11.3, "code": "1440", "change": -0.2, "name": "\u5357\u7d21", "ma2400": 14.56, "ma60": 0.0, "ma10": 11.99, "ma30": 0.0, "ma20": 11.98, "ma5": 11.45, "pct": -1.74, "ma1200": 12.63, "ma480": 11.31, "date": "09/29", "ma720": 12.06}}, {"dk_dies": {"ma240": 0.0, "volume": 198.0, "price": 3.9, "code": "1538", "change": -0.14, "name": "\u6b63\u5cf0\u65b0", "ma2400": 11.58, "ma60": 0.0, "ma10": 4.24, "ma30": 0.0, "ma20": 4.04, "ma5": 4.38, "pct": -3.47, "ma1200": 5.05, "ma480": 4.34, "date": "09/29", "ma720": 4.58}}, {"dk_dies": {"ma240": 0.0, "volume": 906.0, "price": 612.0, "code": "1590", "change": -24.0, "name": "\u4e9e\u5fb7\u5ba2-KY", "ma2400": 0.0, "ma60": 0.0, "ma10": 653.9, "ma30": 0.0, "ma20": 664.3, "ma5": 631.8, "pct": -3.77, "ma1200": 0.0, "ma480": 0.0, "date": "09/29", "ma720": 0.0}}, {"dk_dies": {"ma240": 0.0, "volume": 5546.0, "price": 124.5, "code": "1760", "change": -7.5, "name": "\u5bf6\u9f61\u5bcc\u9326", "ma2400": 0.0, "ma60": 0.0, "ma10": 129.3, "ma30": 125.4, "ma20": 130.7, "ma5": 127.6, "pct": -5.68, "ma1200": 0.0, "ma480": 0.0, "date": "09/29", "ma720": 0.0}}, {"dk_dies": {"ma240": 87.56, "volume": 1567.0, "price": 80.6, "code": "1795", "change": -0.5, "name": "\u7f8e\u6642", "ma2400": 0.0, "ma60": 0.0, "ma10": 82.31, "ma30": 80.83, "ma20": 0.0, "ma5": 81.36, "pct": -0.62, "ma1200": 0.0, "ma480": 0.0, "date": "09/29", "ma720": 0.0}}, {"dk_dies": {"ma240": 18.12, "volume": 56.0, "price": 16.25, "code": "2012", "change": -0.1, "name": "\u6625\u96e8", "ma2400": 0.0, "ma60": 16.86, "ma10": 16.63, "ma30": 16.29, "ma20": 16.63, "ma5": 16.33, "pct": -0.61, "ma1200": 0.0, "ma480": 19.76, "date": "09/29", "ma720": 0.0}}, {"dk_dies": {"ma240": 0.0, "volume": 564.0, "price": 22.5, "code": "2206", "change": -0.1, "name": "\u4e09\u967d\u5de5\u696d", "ma2400": 0.0, "ma60": 0.0, "ma10": 23.12, "ma30": 0.0, "ma20": 23.37, "ma5": 22.6, "pct": -0.44, "ma1200": 0.0, "ma480": 0.0, "date": "09/29", "ma720": 0.0}}, {"dk_dies": {"ma240": 15.08, "volume": 647.0, "price": 15.65, "code": "2402", "change": -0.25, "name": "\u6bc5\u5609", "ma2400": 0.0, "ma60": 0.0, "ma10": 16.51, "ma30": 0.0, "ma20": 16.62, "ma5": 16.21, "pct": -1.57, "ma1200": 16.2, "ma480": 15.04, "date": "09/29", "ma720": 15.76}}, {"dk_dies": {"ma240": 0.0, "volume": 930.0, "price": 29.85, "code": "2436", "change": -0.2, "name": "\u5049\u8a6e\u96fb", "ma2400": 0.0, "ma60": 0.0, "ma10": 30.68, "ma30": 0.0, "ma20": 0.0, "ma5": 30.2, "pct": -0.67, "ma1200": 0.0, "ma480": 0.0, "date": "09/29", "ma720": 0.0}}, {"dk_dies": {"ma240": 9.4, "volume": 755.0, "price": 9.87, "code": "2489", "change": -0.12, "name": "\u745e\u8ed2", "ma2400": 18.18, "ma60": 0.0, "ma10": 10.16, "ma30": 0.0, "ma20": 10.4, "ma5": 9.92, "pct": -1.2, "ma1200": 15.15, "ma480": 10.51, "date": "09/29", "ma720": 11.95}}, {"dk_dies": {"ma240": 19.97, "volume": 490.0, "price": 19.5, "code": "2501", "change": -0.05, "name": "\u570b\u5efa", "ma2400": 0.0, "ma60": 0.0, "ma10": 19.98, "ma30": 19.5, "ma20": 0.0, "ma5": 19.47, "pct": -0.26, "ma1200": 0.0, "ma480": 0.0, "date": "09/29", "ma720": 0.0}}, {"dk_dies": {"ma240": 5.34, "volume": 149.0, "price": 5.19, "code": "2516", "change": -0.06, "name": "\u65b0\u5efa", "ma2400": 7.74, "ma60": 0.0, "ma10": 5.29, "ma30": 0.0, "ma20": 0.0, "ma5": 5.3, "pct": -1.14, "ma1200": 6.31, "ma480": 5.77, "date": "09/29", "ma720": 6.02}}, {"dk_dies": {"ma240": 8.36, "volume": 17680.0, "price": 8.31, "code": "2610", "change": -0.22, "name": "\u83ef\u822a", "ma2400": 11.89, "ma60": 0.0, "ma10": 8.43, "ma30": 0.0, "ma20": 8.76, "ma5": 0.0, "pct": -2.58, "ma1200": 9.9, "ma480": 9.1, "date": "09/29", "ma720": 9.68}}, {"dk_dies": {"ma240": 24.12, "volume": 2.0, "price": 18.9, "code": "2924", "change": -0.5, "name": "\u6771\u51cc-KY", "ma2400": 0.0, "ma60": 19.51, "ma10": 0.0, "ma30": 18.9, "ma20": 18.89, "ma5": 0.0, "pct": -2.58, "ma1200": 43.48, "ma480": 29.27, "date": "09/29", "ma720": 34.91}}, {"dk_dies": {"ma240": 93.82, "volume": 4.0, "price": 76.0, "code": "2926", "change": -2.8, "name": "\u8aa0\u54c1\u751f\u6d3b", "ma2400": 0.0, "ma60": 0.0, "ma10": 0.0, "ma30": 77.91, "ma20": 0.0, "ma5": 76.62, "pct": -3.55, "ma1200": 139.8, "ma480": 110.9, "date": "09/29", "ma720": 119.6}}, {"dk_dies": {"ma240": 11.38, "volume": 6837.0, "price": 9.5, "code": "3049", "change": -0.3, "name": "\u548c\u946b", "ma2400": 10.91, "ma60": 9.99, "ma10": 10.0, "ma30": 9.73, "ma20": 9.9, "ma5": 9.63, "pct": -3.06, "ma1200": 0.0, "ma480": 0.0, "date": "09/29", "ma720": 10.41}}, {"dk_dies": {"ma240": 0.0, "volume": 42.0, "price": 43.6, "code": "3167", "change": -0.2, "name": "\u5927\u91cf", "ma2400": 0.0, "ma60": 0.0, "ma10": 43.86, "ma30": 0.0, "ma20": 43.83, "ma5": 43.21, "pct": -0.46, "ma1200": 0.0, "ma480": 39.5, "date": "09/29", "ma720": 42.82}}, {"dk_dies": {"ma240": 0.0, "volume": 212.0, "price": 17.3, "code": "3232", "change": -0.7, "name": "\u6631\u6377", "ma2400": 23.7, "ma60": 0.0, "ma10": 18.88, "ma30": 17.95, "ma20": 19.06, "ma5": 18.02, "pct": -3.89, "ma1200": 21.75, "ma480": 17.71, "date": "09/29", "ma720": 21.43}}, {"dk_dies": {"ma240": 40.83, "volume": 993.0, "price": 36.55, "code": "3317", "change": -0.95, "name": "\u5c3c\u514b\u68ee", "ma2400": 23.71, "ma60": 0.0, "ma10": 0.0, "ma30": 36.67, "ma20": 37.13, "ma5": 38.18, "pct": -2.53, "ma1200": 0.0, "ma480": 37.67, "date": "09/29", "ma720": 0.0}}, {"dk_dies": {"ma240": 22.37, "volume": 174.0, "price": 18.0, "code": "3508", "change": -0.2, "name": "\u4f4d\u901f", "ma2400": 43.23, "ma60": 0.0, "ma10": 18.56, "ma30": 18.11, "ma20": 0.0, "ma5": 18.41, "pct": -1.1, "ma1200": 0.0, "ma480": 27.76, "date": "09/29", "ma720": 34.42}}, {"dk_dies": {"ma240": 14.2, "volume": 94.0, "price": 10.65, "code": "3522", "change": -0.3, "name": "\u5fa1\u9802", "ma2400": 21.93, "ma60": 10.79, "ma10": 11.54, "ma30": 10.84, "ma20": 11.23, "ma5": 11.24, "pct": -2.74, "ma1200": 0.0, "ma480": 19.72, "date": "09/29", "ma720": 24.47}}, {"dk_dies": {"ma240": 84.26, "volume": 840.0, "price": 83.9, "code": "3596", "change": -0.7, "name": "\u667a\u6613", "ma2400": 0.0, "ma60": 0.0, "ma10": 86.19, "ma30": 84.08, "ma20": 87.6, "ma5": 84.66, "pct": -0.83, "ma1200": 0.0, "ma480": 0.0, "date": "09/29", "ma720": 0.0}}, {"dk_dies": {"ma240": 17.63, "volume": 122.0, "price": 14.8, "code": "3642", "change": -1.2, "name": "\u99ff\u71a0\u96fb", "ma2400": 0.0, "ma60": 16.33, "ma10": 15.13, "ma30": 15.85, "ma20": 15.15, "ma5": 15.22, "pct": -7.5, "ma1200": 19.82, "ma480": 15.75, "date": "09/29", "ma720": 16.51}}, {"dk_dies": {"ma240": 0.0, "volume": 122.0, "price": 43.3, "code": "4433", "change": -0.15, "name": "\u8208\u91c7", "ma2400": 0.0, "ma60": 0.0, "ma10": 44.46, "ma30": 0.0, "ma20": 45.7, "ma5": 43.1, "pct": -0.35, "ma1200": 0.0, "ma480": 0.0, "date": "09/29", "ma720": 0.0}}, {"dk_dies": {"ma240": 12.29, "volume": 49.0, "price": 8.9, "code": "4529", "change": -0.06, "name": "\u6df3\u7d33", "ma2400": 21.1, "ma60": 0.0, "ma10": 9.1, "ma30": 8.94, "ma20": 0.0, "ma5": 9.0, "pct": -0.67, "ma1200": 28.16, "ma480": 16.98, "date": "09/29", "ma720": 21.61}}, {"dk_dies": {"ma240": 23.98, "volume": 5.0, "price": 21.2, "code": "4542", "change": -0.95, "name": "\u79d1\u5da0", "ma2400": 0.0, "ma60": 0.0, "ma10": 21.48, "ma30": 21.46, "ma20": 0.0, "ma5": 21.3, "pct": -4.29, "ma1200": 0.0, "ma480": 23.52, "date": "09/29", "ma720": 25.29}}, {"dk_dies": {"ma240": 35.82, "volume": 340.0, "price": 35.3, "code": "4552", "change": -1.15, "name": "\u529b\u9054-KY", "ma2400": 0.0, "ma60": 0.0, "ma10": 38.07, "ma30": 35.61, "ma20": 0.0, "ma5": 37.13, "pct": -3.16, "ma1200": 0.0, "ma480": 45.63, "date": "09/29", "ma720": 61.34}}, {"dk_dies": {"ma240": 0.0, "volume": 13.0, "price": 37.0, "code": "4556", "change": -0.45, "name": "\u65ed\u7136", "ma2400": 0.0, "ma60": 0.0, "ma10": 0.0, "ma30": 0.0, "ma20": 36.95, "ma5": 0.0, "pct": -1.2, "ma1200": 0.0, "ma480": 0.0, "date": "09/29", "ma720": 0.0}}, {"dk_dies": {"ma240": 0.0, "volume": 49.0, "price": 8.86, "code": "5210", "change": -0.02, "name": "\u5bf6\u78a9", "ma2400": 8.09, "ma60": 0.0, "ma10": 9.35, "ma30": 0.0, "ma20": 9.25, "ma5": 9.2, "pct": -0.23, "ma1200": 0.0, "ma480": 0.0, "date": "09/29", "ma720": 0.0}}, {"dk_dies": {"ma240": 50.82, "volume": 61.0, "price": 44.0, "code": "5285", "change": -0.25, "name": "\u754c\u9716", "ma2400": 0.0, "ma60": 0.0, "ma10": 45.14, "ma30": 44.15, "ma20": 44.29, "ma5": 44.13, "pct": -0.56, "ma1200": 0.0, "ma480": 58.79, "date": "09/29", "ma720": 67.01}}, {"dk_dies": {"ma240": 83.4, "volume": 295.0, "price": 76.4, "code": "6111", "change": -1.9, "name": "\u5927\u5b87\u8cc7", "ma2400": 0.0, "ma60": 0.0, "ma10": 77.14, "ma30": 77.71, "ma20": 0.0, "ma5": 76.18, "pct": -2.43, "ma1200": 0.0, "ma480": 96.14, "date": "09/29", "ma720": 96.42}}, {"dk_dies": {"ma240": 0.0, "volume": 65.0, "price": 40.4, "code": "6184", "change": -0.4, "name": "\u5927\u8c50\u96fb", "ma2400": 47.0, "ma60": 0.0, "ma10": 0.0, "ma30": 40.74, "ma20": 40.43, "ma5": 40.64, "pct": -0.98, "ma1200": 38.6, "ma480": 0.0, "date": "09/29", "ma720": 0.0}}, {"dk_dies": {"ma240": 0.0, "volume": 353.0, "price": 257.5, "code": "6230", "change": -1.0, "name": "\u8d85\u773e", "ma2400": 0.0, "ma60": 0.0, "ma10": 258.4, "ma30": 257.9, "ma20": 259.8, "ma5": 258.3, "pct": -0.39, "ma1200": 0.0, "ma480": 0.0, "date": "09/29", "ma720": 0.0}}, {"dk_dies": {"ma240": 0.0, "volume": 2268.0, "price": 23.85, "code": "6282", "change": -0.15, "name": "\u5eb7\u8212", "ma2400": 24.2, "ma60": 0.0, "ma10": 24.67, "ma30": 0.0, "ma20": 24.96, "ma5": 23.97, "pct": -0.62, "ma1200": 0.0, "ma480": 0.0, "date": "09/29", "ma720": 0.0}}, {"dk_dies": {"ma240": 0.0, "volume": 1078.0, "price": 86.8, "code": "6576", "change": -4.9, "name": "\u9038\u9054", "ma2400": 0.0, "ma60": 0.0, "ma10": 92.32, "ma30": 90.33, "ma20": 0.0, "ma5": 90.92, "pct": -5.34, "ma1200": 0.0, "ma480": 69.47, "date": "09/29", "ma720": 0.0}}, {"dk_dies": {"ma240": 0.0, "volume": 579.0, "price": 9.11, "code": "8093", "change": -0.49, "name": "\u4fdd\u92b3", "ma2400": 7.32, "ma60": 0.0, "ma10": 10.13, "ma30": 9.35, "ma20": 9.96, "ma5": 9.87, "pct": -5.1, "ma1200": 0.0, "ma480": 0.0, "date": "09/29", "ma720": 0.0}}, {"dk_dies": {"ma240": 0.0, "volume": 1293.0, "price": 9.79, "code": "8110", "change": -0.21, "name": "\u83ef\u6771", "ma2400": 11.49, "ma60": 0.0, "ma10": 10.07, "ma30": 9.93, "ma20": 10.16, "ma5": 9.82, "pct": -2.1, "ma1200": 0.0, "ma480": 10.28, "date": "09/29", "ma720": 11.73}}, {"dk_dies": {"ma240": 35.27, "volume": 1.0, "price": 35.3, "code": "8934", "change": -1.4, "name": "\u8861\u5e73", "ma2400": 0.0, "ma60": 0.0, "ma10": 35.77, "ma30": 0.0, "ma20": 0.0, "ma5": 36.42, "pct": -3.81, "ma1200": 39.31, "ma480": 36.9, "date": "09/29", "ma720": 37.31}}, {"dk_dies": {"ma240": 0.0, "volume": 174.0, "price": 11.75, "code": "911622", "change": -1.3, "name": "\u6cf0\u805a\u4ea8-DR", "ma2400": 0.0, "ma60": 0.0, "ma10": 13.17, "ma30": 0.0, "ma20": 0.0, "ma5": 13.98, "pct": -9.96, "ma1200": 9.67, "ma480": 0.0, "date": "09/29", "ma720": 7.82}}, {"dk_dies": {"ma240": 0.0, "volume": 889.0, "price": 11.45, "code": "9136", "change": -1.25, "name": "\u5de8\u9a30-DR", "ma2400": 13.11, "ma60": 0.0, "ma10": 14.77, "ma30": 11.78, "ma20": 0.0, "ma5": 14.25, "pct": -9.84, "ma1200": 10.07, "ma480": 0.0, "date": "09/29", "ma720": 8.29}}, {"dk_dies": {"ma240": 0.0, "volume": 40.0, "price": 40.8, "code": "9931", "change": -0.2, "name": "\u6b23\u9ad8", "ma2400": 0.0, "ma60": 0.0, "ma10": 0.0, "ma30": 40.81, "ma20": 0.0, "ma5": 40.65, "pct": -0.49, "ma1200": 0.0, "ma480": 0.0, "date": "09/29", "ma720": 0.0}}]