[{"p_high": {"code": "00713", "name": "\u5143\u5927\u53f0\u7063\u9ad8\u606f\u4f4e\u6ce2", "date": "10/27", "price": 34.22, "high": 34.35, "low": 33.91, "change": 0.05, "pct": 0.15, "phigh3": 34.35, "dhigh3": -0.38, "plow3": 31.5, "dlow3": 8.63, "phigh6": 34.35, "dhigh6": -0.38, "plow6": 29.75, "dlow6": 15.0, "phigh12": 34.35, "dhigh12": -0.38, "plow12": 24.0, "dlow12": 42.6}}, {"p_high": {"code": "01007T", "name": "\u5146\u8c50\u570b\u6cf0R2", "date": "10/27", "price": 19.03, "high": 19.05, "low": 19.03, "change": 0.0, "pct": 0.0, "phigh3": 19.05, "dhigh3": -0.1, "plow3": 17.84, "dlow3": 6.67, "phigh6": 19.05, "dhigh6": -0.1, "plow6": 17.3, "dlow6": 10.0, "phigh12": 19.05, "dhigh12": -0.1, "plow12": 16.3, "dlow12": 16.8}}, {"p_high": {"code": "020003", "name": "\u7d71\u4e00\u6f32\u5347\u80a1\u5229150N", "date": "10/27", "price": 11.82, "high": 11.82, "low": 11.82, "change": -0.01, "pct": -0.08, "phigh3": 11.82, "dhigh3": 0.0, "plow3": 11.0, "dlow3": 7.45, "phigh6": 11.82, "dhigh6": 0.0, "plow6": 9.94, "dlow6": 18.9, "phigh12": 11.82, "dhigh12": 0.0, "plow12": 7.94, "dlow12": 48.9}}, {"p_high": {"code": "1304", "name": "\u53f0\u805a", "date": "10/27", "price": 18.5, "high": 18.75, "low": 17.75, "change": 0.55, "pct": 3.06, "phigh3": 18.75, "dhigh3": -1.33, "plow3": 11.15, "dlow3": 65.9, "phigh6": 18.75, "dhigh6": -1.33, "plow6": 11.15, "dlow6": 65.9, "phigh12": 18.75, "dhigh12": -1.33, "plow12": 8.11, "dlow12": 128.0}}, {"p_high": {"code": "1309", "name": "\u53f0\u9054\u5316", "date": "10/27", "price": 34.65, "high": 34.65, "low": 31.05, "change": 3.15, "pct": 10.0, "phigh3": 34.65, "dhigh3": 0.0, "plow3": 14.25, "dlow3": 143.0, "phigh6": 34.65, "dhigh6": 0.0, "plow6": 9.42, "dlow6": 268.0, "phigh12": 34.65, "dhigh12": 0.0, "plow12": 6.23, "dlow12": 456.0}}, {"p_high": {"code": "1312", "name": "\u570b\u55ac", "date": "10/27", "price": 22.15, "high": 23.0, "low": 21.35, "change": 0.8, "pct": 3.75, "phigh3": 23.0, "dhigh3": -3.7, "plow3": 13.55, "dlow3": 63.5, "phigh6": 23.0, "dhigh6": -3.7, "plow6": 13.55, "dlow6": 63.5, "phigh12": 23.0, "dhigh12": -3.7, "plow12": 10.65, "dlow12": 108.0}}, {"p_high": {"code": "1414", "name": "\u6771\u548c", "date": "10/27", "price": 10.95, "high": 10.95, "low": 9.89, "change": 0.99, "pct": 9.94, "phigh3": 10.95, "dhigh3": 0.0, "plow3": 6.56, "dlow3": 66.9, "phigh6": 10.95, "dhigh6": 0.0, "plow6": 6.19, "dlow6": 76.9, "phigh12": 10.95, "dhigh12": 0.0, "plow12": 4.92, "dlow12": 123.0}}, {"p_high": {"code": "1435", "name": "\u4e2d\u798f", "date": "10/27", "price": 19.5, "high": 19.5, "low": 17.6, "change": 1.75, "pct": 9.86, "phigh3": 19.5, "dhigh3": 0.0, "plow3": 8.66, "dlow3": 125.0, "phigh6": 19.5, "dhigh6": 0.0, "plow6": 7.95, "dlow6": 145.0, "phigh12": 19.5, "dhigh12": 0.0, "plow12": 6.19, "dlow12": 215.0}}, {"p_high": {"code": "1718", "name": "\u4e2d\u7e96", "date": "10/27", "price": 8.72, "high": 9.1, "low": 8.33, "change": 0.28, "pct": 3.32, "phigh3": 9.1, "dhigh3": -4.18, "plow3": 6.07, "dlow3": 43.7, "phigh6": 9.1, "dhigh6": -4.18, "plow6": 6.06, "dlow6": 43.9, "phigh12": 9.1, "dhigh12": -4.18, "plow12": 4.68, "dlow12": 86.3}}, {"p_high": {"code": "1904", "name": "\u6b63\u9686", "date": "10/27", "price": 35.35, "high": 35.7, "low": 33.6, "change": 1.8, "pct": 5.37, "phigh3": 35.7, "dhigh3": -0.98, "plow3": 23.0, "dlow3": 53.7, "phigh6": 35.7, "dhigh6": -0.98, "plow6": 20.75, "dlow6": 70.4, "phigh12": 35.7, "dhigh12": -0.98, "plow12": 17.55, "dlow12": 101.0}}, {"p_high": {"code": "2108", "name": "\u5357\u5e1d", "date": "10/27", "price": 69.5, "high": 73.3, "low": 65.9, "change": 2.8, "pct": 4.2, "phigh3": 73.3, "dhigh3": -5.18, "plow3": 34.1, "dlow3": 104.0, "phigh6": 73.3, "dhigh6": -5.18, "plow6": 29.25, "dlow6": 138.0, "phigh12": 73.3, "dhigh12": -5.18, "plow12": 22.4, "dlow12": 210.0}}, {"p_high": {"code": "2204", "name": "\u4e2d\u83ef", "date": "10/27", "price": 45.5, "high": 45.5, "low": 45.15, "change": 0.1, "pct": 0.22, "phigh3": 45.5, "dhigh3": 0.0, "plow3": 37.1, "dlow3": 22.6, "phigh6": 45.5, "dhigh6": 0.0, "plow6": 29.45, "dlow6": 54.5, "phigh12": 45.5, "dhigh12": 0.0, "plow12": 24.4, "dlow12": 86.5}}, {"p_high": {"code": "2302", "name": "\u9e97\u6b63", "date": "10/27", "price": 20.15, "high": 20.15, "low": 18.5, "change": 1.8, "pct": 9.81, "phigh3": 20.15, "dhigh3": 0.0, "plow3": 8.5, "dlow3": 137.0, "phigh6": 20.15, "dhigh6": 0.0, "plow6": 6.97, "dlow6": 189.0, "phigh12": 20.15, "dhigh12": 0.0, "plow12": 4.43, "dlow12": 355.0}}, {"p_high": {"code": "2355", "name": "\u656c\u9d6c", "date": "10/27", "price": 32.8, "high": 33.5, "low": 31.7, "change": 0.2, "pct": 0.61, "phigh3": 33.5, "dhigh3": -2.09, "plow3": 24.5, "dlow3": 33.9, "phigh6": 33.5, "dhigh6": -2.09, "plow6": 21.65, "dlow6": 51.5, "phigh12": 34.5, "dhigh12": -4.93, "plow12": 18.7, "dlow12": 75.4}}, {"p_high": {"code": "2426", "name": "\u9f0e\u5143", "date": "10/27", "price": 18.25, "high": 18.35, "low": 17.25, "change": 0.65, "pct": 3.69, "phigh3": 18.35, "dhigh3": -0.54, "plow3": 12.8, "dlow3": 42.6, "phigh6": 18.35, "dhigh6": -0.54, "plow6": 12.4, "dlow6": 47.2, "phigh12": 18.35, "dhigh12": -0.54, "plow12": 8.1, "dlow12": 125.0}}, {"p_high": {"code": "3028", "name": "\u589e\u4f60\u5f37", "date": "10/27", "price": 21.6, "high": 21.65, "low": 21.35, "change": 0.05, "pct": 0.23, "phigh3": 21.65, "dhigh3": -0.23, "plow3": 18.3, "dlow3": 18.0, "phigh6": 21.65, "dhigh6": -0.23, "plow6": 18.25, "dlow6": 18.4, "phigh12": 21.65, "dhigh12": -0.23, "plow12": 15.35, "dlow12": 40.7}}, {"p_high": {"code": "3067", "name": "\u5168\u57df", "date": "10/27", "price": 34.85, "high": 36.8, "low": 34.75, "change": 0.6, "pct": 1.75, "phigh3": 36.8, "dhigh3": -5.3, "plow3": 24.05, "dlow3": 44.9, "phigh6": 36.8, "dhigh6": -5.3, "plow6": 23.0, "dlow6": 51.5, "phigh12": 49.3, "dhigh12": -29.3, "plow12": 10.6, "dlow12": 229.0}}, {"p_high": {"code": "3226", "name": "\u81f3\u5bf6\u96fb", "date": "10/27", "price": 57.5, "high": 58.0, "low": 57.0, "change": 0.2, "pct": 0.35, "phigh3": 58.0, "dhigh3": -0.86, "plow3": 51.6, "dlow3": 11.4, "phigh6": 58.0, "dhigh6": -0.86, "plow6": 50.9, "dlow6": 13.0, "phigh12": 59.0, "dhigh12": -2.54, "plow12": 44.0, "dlow12": 30.7}}, {"p_high": {"code": "3372", "name": "\u5178\u7bc4", "date": "10/27", "price": 11.5, "high": 12.0, "low": 11.2, "change": 0.35, "pct": 3.14, "phigh3": 12.0, "dhigh3": -4.17, "plow3": 8.25, "dlow3": 39.4, "phigh6": 12.0, "dhigh6": -4.17, "plow6": 8.25, "dlow6": 39.4, "phigh12": 12.0, "dhigh12": -4.17, "plow12": 6.58, "dlow12": 74.8}}, {"p_high": {"code": "3426", "name": "\u53f0\u8208", "date": "10/27", "price": 46.9, "high": 47.95, "low": 46.2, "change": 0.8, "pct": 1.74, "phigh3": 47.95, "dhigh3": -2.19, "plow3": 35.0, "dlow3": 34.0, "phigh6": 47.95, "dhigh6": -2.19, "plow6": 33.85, "dlow6": 38.6, "phigh12": 47.95, "dhigh12": -2.19, "plow12": 25.75, "dlow12": 82.1}}, {"p_high": {"code": "3545", "name": "\u6566\u6cf0", "date": "10/27", "price": 48.4, "high": 50.0, "low": 46.15, "change": 1.4, "pct": 2.98, "phigh3": 50.0, "dhigh3": -3.2, "plow3": 30.05, "dlow3": 61.1, "phigh6": 50.0, "dhigh6": -3.2, "plow6": 29.25, "dlow6": 65.5, "phigh12": 50.0, "dhigh12": -3.2, "plow12": 22.45, "dlow12": 116.0}}, {"p_high": {"code": "3596", "name": "\u667a\u6613", "date": "10/27", "price": 103.5, "high": 104.0, "low": 98.0, "change": 4.1, "pct": 4.12, "phigh3": 104.0, "dhigh3": -0.48, "plow3": 72.0, "dlow3": 43.8, "phigh6": 104.0, "dhigh6": -0.48, "plow6": 72.0, "dlow6": 43.8, "phigh12": 104.0, "dhigh12": -0.48, "plow12": 55.0, "dlow12": 88.2}}, {"p_high": {"code": "3709", "name": "\u946b\u806f\u5927\u6295\u63a7", "date": "10/27", "price": 23.2, "high": 24.2, "low": 23.1, "change": 0.8, "pct": 3.57, "phigh3": 24.2, "dhigh3": -4.13, "plow3": 19.65, "dlow3": 18.1, "phigh6": 24.2, "dhigh6": -4.13, "plow6": 19.4, "dlow6": 19.6, "phigh12": 24.2, "dhigh12": -4.13, "plow12": 16.75, "dlow12": 38.5}}, {"p_high": {"code": "4419", "name": "\u5143\u52dd", "date": "10/27", "price": 9.81, "high": 9.81, "low": 9.81, "change": 0.89, "pct": 9.98, "phigh3": 9.81, "dhigh3": 0.0, "plow3": 6.3, "dlow3": 55.7, "phigh6": 9.81, "dhigh6": 0.0, "plow6": 5.9, "dlow6": 66.3, "phigh12": 9.81, "dhigh12": 0.0, "plow12": 4.3, "dlow12": 128.0}}, {"p_high": {"code": "4735", "name": "\u8c6a\u5c55", "date": "10/27", "price": 136.0, "high": 137.5, "low": 132.5, "change": 1.5, "pct": 1.12, "phigh3": 137.5, "dhigh3": -1.09, "plow3": 90.0, "dlow3": 51.1, "phigh6": 137.5, "dhigh6": -1.09, "plow6": 66.2, "dlow6": 105.0, "phigh12": 137.5, "dhigh12": -1.09, "plow12": 44.4, "dlow12": 206.0}}, {"p_high": {"code": "4930", "name": "\u71e6\u661f\u7db2", "date": "10/27", "price": 15.7, "high": 16.0, "low": 14.95, "change": 0.55, "pct": 3.63, "phigh3": 16.0, "dhigh3": -1.88, "plow3": 10.2, "dlow3": 53.9, "phigh6": 16.0, "dhigh6": -1.88, "plow6": 9.32, "dlow6": 68.4, "phigh12": 16.0, "dhigh12": -1.88, "plow12": 6.6, "dlow12": 138.0}}, {"p_high": {"code": "5425", "name": "\u53f0\u534a", "date": "10/27", "price": 48.8, "high": 49.3, "low": 46.6, "change": 1.35, "pct": 2.85, "phigh3": 49.3, "dhigh3": -1.01, "plow3": 34.5, "dlow3": 41.4, "phigh6": 49.3, "dhigh6": -1.01, "plow6": 34.5, "dlow6": 41.4, "phigh12": 55.5, "dhigh12": -12.1, "plow12": 25.3, "dlow12": 92.9}}, {"p_high": {"code": "5521", "name": "\u5de5\u4fe1", "date": "10/27", "price": 12.55, "high": 13.1, "low": 12.4, "change": 0.05, "pct": 0.4, "phigh3": 13.1, "dhigh3": -4.2, "plow3": 9.45, "dlow3": 32.8, "phigh6": 13.1, "dhigh6": -4.2, "plow6": 7.99, "dlow6": 57.1, "phigh12": 13.1, "dhigh12": -4.2, "plow12": 5.31, "dlow12": 136.0}}, {"p_high": {"code": "5543", "name": "\u6853\u9f0e-KY", "date": "10/27", "price": 55.2, "high": 57.8, "low": 55.1, "change": 0.0, "pct": 0.0, "phigh3": 57.8, "dhigh3": -4.5, "plow3": 41.7, "dlow3": 32.4, "phigh6": 57.8, "dhigh6": -4.5, "plow6": 19.95, "dlow6": 177.0, "phigh12": 57.8, "dhigh12": -4.5, "plow12": 18.35, "dlow12": 201.0}}, {"p_high": {"code": "5603", "name": "\u9678\u6d77", "date": "10/27", "price": 22.1, "high": 25.3, "low": 22.0, "change": -1.8, "pct": -7.53, "phigh3": 25.3, "dhigh3": -12.6, "plow3": 9.6, "dlow3": 130.0, "phigh6": 25.3, "dhigh6": -12.6, "plow6": 9.26, "dlow6": 139.0, "phigh12": 25.3, "dhigh12": -12.6, "plow12": 8.85, "dlow12": 150.0}}, {"p_high": {"code": "6204", "name": "\u827e\u83ef", "date": "10/27", "price": 89.1, "high": 92.1, "low": 85.5, "change": 3.5, "pct": 4.09, "phigh3": 92.1, "dhigh3": -3.26, "plow3": 35.9, "dlow3": 148.0, "phigh6": 92.1, "dhigh6": -3.26, "plow6": 23.9, "dlow6": 273.0, "phigh12": 92.1, "dhigh12": -3.26, "plow12": 17.0, "dlow12": 424.0}}, {"p_high": {"code": "6241", "name": "\u6613\u901a\u5c55", "date": "10/27", "price": 29.9, "high": 32.0, "low": 29.2, "change": 0.75, "pct": 2.57, "phigh3": 32.0, "dhigh3": -6.56, "plow3": 16.6, "dlow3": 80.1, "phigh6": 32.0, "dhigh6": -6.56, "plow6": 9.8, "dlow6": 205.0, "phigh12": 32.0, "dhigh12": -6.56, "plow12": 9.45, "dlow12": 216.0}}, {"p_high": {"code": "6472", "name": "\u4fdd\u745e", "date": "10/27", "price": 232.5, "high": 233.5, "low": 221.5, "change": 6.0, "pct": 2.65, "phigh3": 233.5, "dhigh3": -0.43, "plow3": 140.0, "dlow3": 66.1, "phigh6": 233.5, "dhigh6": -0.43, "plow6": 140.0, "dlow6": 66.1, "phigh12": 233.5, "dhigh12": -0.43, "plow12": 108.0, "dlow12": 115.0}}, {"p_high": {"code": "6477", "name": "\u5b89\u96c6", "date": "10/27", "price": 64.9, "high": 68.4, "low": 63.0, "change": 1.1, "pct": 1.72, "phigh3": 68.4, "dhigh3": -5.12, "plow3": 33.15, "dlow3": 95.8, "phigh6": 68.4, "dhigh6": -5.12, "plow6": 19.2, "dlow6": 238.0, "phigh12": 68.4, "dhigh12": -5.12, "plow12": 15.4, "dlow12": 321.0}}, {"p_high": {"code": "6548", "name": "\u9577\u79d1*", "date": "10/27", "price": 48.05, "high": 49.8, "low": 47.3, "change": -0.15, "pct": -0.31, "phigh3": 49.8, "dhigh3": -3.51, "plow3": 29.75, "dlow3": 61.5, "phigh6": 49.8, "dhigh6": -3.51, "plow6": 28.1, "dlow6": 71.0, "phigh12": 49.8, "dhigh12": -3.51, "plow12": 17.2, "dlow12": 179.0}}, {"p_high": {"code": "6582", "name": "\u7533\u8c50", "date": "10/27", "price": 214.5, "high": 226.5, "low": 211.5, "change": 1.0, "pct": 0.47, "phigh3": 226.5, "dhigh3": -5.3, "plow3": 127.0, "dlow3": 68.9, "phigh6": 226.5, "dhigh6": -5.3, "plow6": 88.0, "dlow6": 144.0, "phigh12": 226.5, "dhigh12": -5.3, "plow12": 52.8, "dlow12": 306.0}}, {"p_high": {"code": "8047", "name": "\u661f\u96f2", "date": "10/27", "price": 11.45, "high": 11.5, "low": 11.3, "change": 0.05, "pct": 0.44, "phigh3": 11.5, "dhigh3": -0.43, "plow3": 9.27, "dlow3": 23.5, "phigh6": 11.5, "dhigh6": -0.43, "plow6": 9.14, "dlow6": 25.3, "phigh12": 12.7, "dhigh12": -9.84, "plow12": 9.14, "dlow12": 25.3}}, {"p_high": {"code": "8085", "name": "\u798f\u83ef", "date": "10/27", "price": 7.0, "high": 7.48, "low": 6.96, "change": 0.04, "pct": 0.57, "phigh3": 7.48, "dhigh3": -6.42, "plow3": 3.92, "dlow3": 78.6, "phigh6": 7.48, "dhigh6": -6.42, "plow6": 3.42, "dlow6": 105.0, "phigh12": 7.48, "dhigh12": -6.42, "plow12": 3.0, "dlow12": 133.0}}, {"p_high": {"code": "8240", "name": "\u83ef\u5b8f", "date": "10/27", "price": 34.05, "high": 34.9, "low": 31.75, "change": 2.3, "pct": 7.24, "phigh3": 34.9, "dhigh3": -2.44, "plow3": 23.75, "dlow3": 43.4, "phigh6": 34.9, "dhigh6": -2.44, "plow6": 23.05, "dlow6": 47.7, "phigh12": 34.9, "dhigh12": -2.44, "plow12": 16.2, "dlow12": 110.0}}, {"p_high": {"code": "8930", "name": "\u9752\u92fc", "date": "10/27", "price": 13.15, "high": 13.5, "low": 12.9, "change": 0.35, "pct": 2.73, "phigh3": 13.5, "dhigh3": -2.59, "plow3": 10.8, "dlow3": 21.8, "phigh6": 13.5, "dhigh6": -2.59, "plow6": 10.8, "dlow6": 21.8, "phigh12": 14.15, "dhigh12": -7.07, "plow12": 9.41, "dlow12": 39.7}}]